funda_monitor/__init__.py
funda_monitor/config/__init__.py
funda_monitor/config/config.yaml
funda_monitor/config/core.py
funda_monitor/preprocess.py
funda_monitor/scrape.py
funda_monitor/utils.py
funda_monitor/VERSION
funda_monitor-1.2.0.dist-info/LICENSE
funda_monitor-1.2.0.dist-info/METADATA
funda_monitor-1.2.0.dist-info/WHEEL
funda_monitor-1.2.0.dist-info/RECORD
