Metadata-Version: 2.3
Name: funda-monitor
Version: 1.2.0
Summary: FundaMonitor provides the easiest way to monitor real estate data from Funda, the Dutch housing website. You can track houses either for sale or for rent, and access historical data from the past few years.
Author: Will Chien
Requires-Python: >=3.8,<4.0
Classifier: Programming Language :: Python :: 3
Classifier: Programming Language :: Python :: 3.8
Classifier: Programming Language :: Python :: 3.9
Classifier: Programming Language :: Python :: 3.10
Classifier: Programming Language :: Python :: 3.11
Classifier: Programming Language :: Python :: 3.12
Classifier: Programming Language :: Python :: 3.13
Requires-Dist: beautifulsoup4 (>=4.12.0,<5.0.0)
Requires-Dist: diot (>=0.1.6,<0.2.0)
Requires-Dist: lxml (>=5.1.0,<6.0.0)
Requires-Dist: numpy (>=1.26.0,<2.0.0)
Requires-Dist: pandas (>=2.2.0,<3.0.0)
Requires-Dist: python-dateutil (>=2.8.2,<3.0.0)
Requires-Dist: pyyaml (>=6.0,<7.0)
Requires-Dist: requests (>=2.31.0,<3.0.0)
Requires-Dist: selenium (>=4.18.0,<5.0.0)
Requires-Dist: setuptools (>=69.0.0,<70.0.0)
Requires-Dist: tqdm (>=4.66.0,<5.0.0)
